RahebPDF/__init__.py
RahebPDF-0.2.dist-info/METADATA
RahebPDF-0.2.dist-info/WHEEL
RahebPDF-0.2.dist-info/top_level.txt
RahebPDF-0.2.dist-info/RECORD
